myutils/Remove_pdf_fig_watermark.py
myutils/Remove_pdf_watermark.py
myutils/__init__.py
myutils/batch_print_pdf.py
myutils/batch_renamer.py
myutils/combine_images.py
myutils/combine_images_vertically.py
myutils/date_calculator.py
myutils/gis_map.py
myutils/launcher.py
myutils/pdf_extractor_gui.py
myutils/pdf_variable_extractor_from_template.py
myutils/sign_report_generator.py
myutils/sign_report_json_builder.py
myutils/tools.json
myutils/utils.py
myutils/word2excel.py
myutils_xsy-0.1.1.dist-info/METADATA
myutils_xsy-0.1.1.dist-info/WHEEL
myutils_xsy-0.1.1.dist-info/entry_points.txt
myutils_xsy-0.1.1.dist-info/top_level.txt
myutils_xsy-0.1.1.dist-info/RECORD
